{"peak_balance": 0.0, "closed_trades": [{"symbol": "BTC/USDT:USDT", "side": "long", "entry": 65390.4, "exit": 65426.1, "entry_price": 65390.4, "exit_price": 65426.1, "amount": 0.0022939147030756808, "margin": 15.0, "pnl_usdt": -0.09810724510020487, "pnl_pct": -0.6540483006680324, "fees_usdt": 0.18, "funding_usdt": 0.0, "net_pnl": -0.09810724510020487, "reason": "promote_reset", "exit_reason": "promote_reset", "strategy": "htf_l2_anticipation", "opened_at": 1784602878.885437, "closed_at": 1784603114.262843, "entry_strength": 0.0, "confidence": 0, "ensemble_layers": "", "entry_snapshot": {"ts": 1784602879, "symbol": "BTC/USDT:USDT", "direction": "long", "slot": "HTF_L2_PAPER", "strategy": "htf_l2_anticipation", "strength": 0.84, "confidence": 5, "price": 65390.4, "ob": {"imbalance": 0.143, "bid_walls": 2, "ask_walls": 1, "spread_pct": 0.0002, "bid_depth_usdt": 827972.7908, "ask_depth_usdt": 620822.9677, "first_bid_wall": 65371.3, "first_ask_wall": 65461.5}, "flow": {"buy_ratio": 0.765, "cvd_slope": 1.0, "divergence": null, "large_trade_bias": 0.08, "trade_count": 27}, "regime": {"label": "CHOPPY", "adx": 17.0, "atr_pct": 0.0011, "above_ema200": true, "ema_stack_bull": true, "ema_stack_bear": false, "vol_ratio": 0.43}, "htf_adx": 27.6, "rsi": 57.73, "rsi_fast": 66.764, "ema21_dist_pct": 0.0879, "ema50_dist_pct": 0.1149, "vwap_dist_pct": 0.0444}, "duration_s": 235.37742614746094, "gate_tags": "none", "adopted": false, "adopted_at": 0.0, "peak_price": 65390.4, "scaled_out": false}], "trade_results": [], "positions": {"BTC/USDT:USDT": {"symbol": "BTC/USDT:USDT", "side": "long", "entry_price": 65429.0, "amount": 0.002, "margin": 13.0858, "stop_loss": 64774.71, "take_profit": 66737.58, "peak_price": 65429.0, "trailing_stop_price": null, "entry_cycle": 9, "opened_at": 1784603428.6717818, "strategy": "htf_l2_anticipation", "entry_strength": 0.84, "confidence": 0, "ensemble_layers": "", "entry_snapshot": {"ts": 1784603430, "symbol": "BTC/USDT:USDT", "direction": "long", "slot": "HTF_L2_PAPER", "strategy": "htf_l2_anticipation", "strength": 0.84, "confidence": 4, "price": 65429.0, "ob": {"imbalance": 0.021, "bid_walls": 0, "ask_walls": 0, "spread_pct": 0.0002, "bid_depth_usdt": 475341.57070000004, "ask_depth_usdt": 455980.6738, "first_bid_wall": null, "first_ask_wall": null}, "flow": {"buy_ratio": 0.593, "cvd_slope": 1.0, "divergence": null, "large_trade_bias": 0.16, "trade_count": 132}, "regime": {"label": "CHOPPY", "adx": 17.4, "atr_pct": 0.00117, "above_ema200": true, "ema_stack_bull": true, "ema_stack_bear": false, "vol_ratio": 1.61}, "htf_adx": 28.2, "rsi": 58.508, "rsi_fast": 68.27, "ema21_dist_pct": 0.1352, "ema50_dist_pct": 0.1679, "vwap_dist_pct": 0.0957}, "exchange_sl_price": 64774.71, "sl_ratcheted": false, "scaled_out": false, "adopted": false, "adopted_at": 0.0, "gate_tags": "none"}}}